{
    "result": [
        {
            "text": " Dear 200 Gold Monthly 6:00 PM",
            "link1": "https://hinduwb.files.wordpress.com/2023/06/th170623.pdf",
            "link2": "https://hinduwb.files.wordpress.com/2023/06/th170623.pdf"
        },
        {
            "text": "Dear 500 BI-Monthly 10/06/23",
            "link1": "https://hinduwb.files.wordpress.com/2023/06/fb100623.pdf",
            "link2": "https://hinduwb.files.wordpress.com/2023/06/fb100623.pdf"
        },
        {
            "text": "Dear 200 Monthly 27/05/23",
            "link1": "https://hinduwb.files.wordpress.com/2023/05/th270523.pdf",
            "link2": "https://hinduwb.files.wordpress.com/2023/05/th270523.pdf"
        },
        {
            "text": "DEAR 500 MONTHLY 20/05/23",
            "link1": "https://hinduwb.files.wordpress.com/2023/05/mf200523.pdf",
            "link2": "https://hinduwb.files.wordpress.com/2023/05/mf200523.pdf"
        },
        {
            "text": "DEAR 1000 MONTHLY 06/05/23",
            "link1": "https://hinduwb.files.wordpress.com/2023/05/ay060523.pdf",
            "link2": "https://hinduwb.files.wordpress.com/2023/05/ay060523.pdf"
        },
        {
            "text": "DEAR 500 MONTHLY 29/04/23",
            "link1": "https://hinduwb.files.wordpress.com/2023/04/mf290423.pdf",
            "link2": "https://hinduwb.files.wordpress.com/2023/04/mf290423.pdf"
        },
        {
            "text": "BAISAKHI BUMPER 15/04/23",
            "link1": "https://hinduwb.files.wordpress.com/2023/04/bb150423.pdf",
            "link2": "https://hinduwb.files.wordpress.com/2023/04/bb150423.pdf"
        },
        {
            "text": "Dear 200 Monthly 08/04/23",
            "link1": "https://hinduwb.files.wordpress.com/2023/04/th080423.pdf",
            "link2": "https://hinduwb.files.wordpress.com/2023/04/th080423.pdf"
        },
        {
            "text": "Holi Bumper 11/03/23",
            "link1": "https://hinduwb.files.wordpress.com/2023/04/nh110323.pdf",
            "link2": "https://hinduwb.files.wordpress.com/2023/04/nh110323.pdf"
        }
    ],
    "ver": "31",
    "ver2": "14"
}
